pyani/__init__.py
pyani/anib.py
pyani/anim.py
pyani/pyani_config.py
pyani/pyani_files.py
pyani/pyani_graphics.py
pyani/pyani_jobs.py
pyani/pyani_tools.py
pyani/run_multiprocessing.py
pyani/run_sge.py
pyani/tetra.py
pyani-0.2.12.data/scripts/average_nucleotide_identity.py
pyani-0.2.12.data/scripts/delta_filter_wrapper.py
pyani-0.2.12.data/scripts/genbank_get_genomes_by_taxon.py
pyani-0.2.12.dist-info/LICENSE
pyani-0.2.12.dist-info/METADATA
pyani-0.2.12.dist-info/WHEEL
pyani-0.2.12.dist-info/top_level.txt
pyani-0.2.12.dist-info/RECORD
