Metadata-Version: 2.1
Name: pyani
Version: 0.2.12
Summary: pyani provides a package and script for calculation of genome-scale average nucleotide identity.
Home-page: http://widdowquinn.github.io/pyani/
Download-URL: https://github.com/widdowquinn/pyani/releases
Author: Leighton Pritchard
Author-email: leighton.pritchard@hutton.ac.uk
License: MIT
Keywords: genome bioinformatics sequence
Platform: Posix; MacOS X
Classifier: Development Status :: 4 - Beta
Classifier: Environment :: Console
Classifier: Intended Audience :: Science/Research
Classifier: License :: OSI Approved :: MIT License
Classifier: Natural Language :: English
Classifier: Operating System :: MacOS :: MacOS X
Classifier: Operating System :: POSIX :: Linux
Classifier: Programming Language :: Python
Classifier: Programming Language :: Python :: 3
Classifier: Programming Language :: Python :: 3.5
Classifier: Programming Language :: Python :: 3.6
Classifier: Topic :: Scientific/Engineering :: Bio-Informatics
License-File: LICENSE
Requires-Dist: biopython
Requires-Dist: matplotlib
Requires-Dist: pandas
Requires-Dist: scipy
Requires-Dist: seaborn
